microservice_chassis/AuthManager.py
microservice_chassis/ConsulClient.py
microservice_chassis/PublicKey.py
microservice_chassis/RabbitMQConsumerPublisher.py
microservice_chassis/__init__.py
microservice_chassis/config.py
microservice_chassis/db_methods.py
microservice_chassis-0.3.32.dist-info/METADATA
microservice_chassis-0.3.32.dist-info/WHEEL
microservice_chassis-0.3.32.dist-info/top_level.txt
microservice_chassis-0.3.32.dist-info/RECORD
