Metadata-Version: 2.1
Name: microservice_chassis
Version: 0.3.32
Summary: Chassis para microserviccdios en Python
Home-page: https://github.com/tuusuario/microservice_chassis
Author: Microservice chassis
Requires-Dist: PyJWT
Requires-Dist: SQLAlchemy
